spyne_smev/__init__.py
spyne_smev/_base.py
spyne_smev/_utils.py
spyne_smev/_xmlns.py
spyne_smev/application.py
spyne_smev/client.py
spyne_smev/crypto.py
spyne_smev/fault.py
spyne_smev/server/__init__.py
spyne_smev/server/django.py
spyne_smev/server/wsgi.py
spyne_smev/smev255/__init__.py
spyne_smev/smev255/model.py
spyne_smev/smev256/__init__.py
spyne_smev/smev256/model.py
spyne_smev/wsse/__init__.py
spyne_smev/wsse/protocols.py
spyne_smev/wsse/utils.py
spyne_smev/xsd/smev248-atachments.xsd
spyne_smev/xsd/smev248.xsd
spyne_smev/xsd/smev255-atachments.xsd
spyne_smev/xsd/smev255.xsd
spyne_smev/xsd/smev256-atachments.xsd
spyne_smev/xsd/smev256.xsd
spyne_smev/xsd/xop-include.xsd
m3_spyne_smev-1.0.1.dist-info/LICENSE
m3_spyne_smev-1.0.1.dist-info/METADATA
m3_spyne_smev-1.0.1.dist-info/WHEEL
m3_spyne_smev-1.0.1.dist-info/dependency_links.txt
m3_spyne_smev-1.0.1.dist-info/top_level.txt
m3_spyne_smev-1.0.1.dist-info/RECORD
