Metadata-Version: 2.1
Name: m3-spyne-smev
Version: 1.0.1
Summary: Набор протоколов фреймворка spyne для работы со СМЭВ.
Home-page: https://stash.bars-open.ru/projects/M3/repos/spyne-smev/browse
Author: BARS Group
Author-email: bars@bars-open.ru
License: MIT
Classifier: Intended Audience :: Developers
Classifier: Environment :: Web Environment
Classifier: Natural Language :: Russian
Classifier: Natural Language :: English
Classifier: Operating System :: OS Independent
Classifier: Programming Language :: Python
Classifier: License :: OSI Approved :: MIT License
Classifier: Development Status :: 5 - Production/Stable
Classifier: Programming Language :: Python
Classifier: Programming Language :: Python :: 3.6
Classifier: Programming Language :: Python :: 3.7
Classifier: Programming Language :: Python :: 3.8
Classifier: Programming Language :: Python :: 3.9
Classifier: Framework :: Django :: 2.0
Classifier: Framework :: Django :: 2.1
Classifier: Framework :: Django :: 2.2
License-File: LICENSE
Requires-Dist: lxml
Requires-Dist: cryptography <4,>=3.4.8
Requires-Dist: requests <3,>=2
Requires-Dist: spyne <3,>=2.11
Requires-Dist: suds-py3 <2,>=1.3.3.0 ; python_version > '2.7'
